CHANGES.rst
CONTRIBUTORS.rst
MANIFEST.in
README.rst
setup.cfg
setup.py
docs/LICENSE.GPL
docs/LICENSE.rst
docs/index.rst
src/urban/__init__.py
src/urban.vocabulary.egg-info/PKG-INFO
src/urban.vocabulary.egg-info/SOURCES.txt
src/urban.vocabulary.egg-info/dependency_links.txt
src/urban.vocabulary.egg-info/entry_points.txt
src/urban.vocabulary.egg-info/namespace_packages.txt
src/urban.vocabulary.egg-info/not-zip-safe
src/urban.vocabulary.egg-info/requires.txt
src/urban.vocabulary.egg-info/top_level.txt
src/urban/vocabulary/__init__.py
src/urban/vocabulary/configure.zcml
src/urban/vocabulary/interfaces.py
src/urban/vocabulary/setuphandlers.py
src/urban/vocabulary/testing.py
src/urban/vocabulary/testing.zcml
src/urban/vocabulary/utils.py
src/urban/vocabulary/ws.py
src/urban/vocabulary/browser/__init__.py
src/urban/vocabulary/browser/configure.zcml
src/urban/vocabulary/browser/controlpanel.py
src/urban/vocabulary/browser/webservice.py
src/urban/vocabulary/locales/update.sh
src/urban/vocabulary/locales/urban.vocabulary.pot
src/urban/vocabulary/locales/fr/LC_MESSAGES/urban.vocabulary.mo
src/urban/vocabulary/locales/fr/LC_MESSAGES/urban.vocabulary.po
src/urban/vocabulary/profiles/default/browserlayer.xml
src/urban/vocabulary/profiles/default/controlpanel.xml
src/urban/vocabulary/profiles/default/metadata.xml
src/urban/vocabulary/profiles/default/registry.xml
src/urban/vocabulary/profiles/testing/metadata.xml
src/urban/vocabulary/tests/__init__.py
src/urban/vocabulary/tests/test_setup.py
src/urban/vocabulary/tests/test_utils.py
src/urban/vocabulary/tests/test_vocabularies.py
src/urban/vocabulary/tests/test_ws.py
src/urban/vocabulary/vocabularies/__init__.py
src/urban/vocabulary/vocabularies/areaplan.py
src/urban/vocabulary/vocabularies/base.py
src/urban/vocabulary/vocabularies/catchmentarea.py
src/urban/vocabulary/vocabularies/configure.zcml
src/urban/vocabulary/vocabularies/karstic.py
src/urban/vocabulary/vocabularies/natura2000.py
src/urban/vocabulary/vocabularies/noteworthytrees.py
src/urban/vocabulary/vocabularies/parcellings.py
src/urban/vocabulary/vocabularies/pcazones.py
src/urban/vocabulary/vocabularies/protectedbuilding.py
src/urban/vocabulary/vocabularies/reparcelling.py
src/urban/vocabulary/vocabularies/sar.py
src/urban/vocabulary/vocabularies/solzones.py
